izzy_devices/__init__.py
izzy_devices/client.py
izzy_devices/client_status.py
izzy_devices/logger.py
izzy_devices/server.py
izzy_devices/server_status.py
izzy_devices-0.2.0.dist-info/METADATA
izzy_devices-0.2.0.dist-info/WHEEL
izzy_devices-0.2.0.dist-info/RECORD
