Metadata-Version: 2.4
Name: izzy-devices
Version: 0.2.0
Summary: Client and Server classes for the IZZY Project.
Project-URL: repository, https://github.com/rmdPurdue/izzy-devices
Author-email: Rich Dionne <rdionne@purdue.edu>
Classifier: Development Status :: 3 - Alpha
Classifier: License :: OSI Approved :: GNU General Public License v3 (GPLv3)
Classifier: Programming Language :: Python
Requires-Python: >=3.13
